CHANGES.rst
CONTRIBUTORS.rst
DEVELOP.rst
LICENSE.GPL
LICENSE.rst
MANIFEST.in
README.rst
constraints.txt
constraints_plone52.txt
requirements.txt
setup.cfg
setup.py
tox.ini
docs/conf.py
docs/index.rst
src/affinitic/__init__.py
src/affinitic.privatefolder.egg-info/PKG-INFO
src/affinitic.privatefolder.egg-info/SOURCES.txt
src/affinitic.privatefolder.egg-info/dependency_links.txt
src/affinitic.privatefolder.egg-info/entry_points.txt
src/affinitic.privatefolder.egg-info/namespace_packages.txt
src/affinitic.privatefolder.egg-info/not-zip-safe
src/affinitic.privatefolder.egg-info/requires.txt
src/affinitic.privatefolder.egg-info/top_level.txt
src/affinitic/privatefolder/__init__.py
src/affinitic/privatefolder/configure.zcml
src/affinitic/privatefolder/interfaces.py
src/affinitic/privatefolder/setuphandlers.py
src/affinitic/privatefolder/testing.py
src/affinitic/privatefolder/locales/README.rst
src/affinitic/privatefolder/locales/__init__.py
src/affinitic/privatefolder/locales/affinitic.privatefolder.pot
src/affinitic/privatefolder/locales/plone.pot
src/affinitic/privatefolder/locales/update.sh
src/affinitic/privatefolder/locales/fr/LC_MESSAGES/affinitic.privatefolder.po
src/affinitic/privatefolder/locales/fr/LC_MESSAGES/plone.po
src/affinitic/privatefolder/profiles/default/browserlayer.xml
src/affinitic/privatefolder/profiles/default/metadata.xml
src/affinitic/privatefolder/profiles/default/types.xml
src/affinitic/privatefolder/profiles/default/workflows.xml
src/affinitic/privatefolder/profiles/default/types/PrivateFolder.xml
src/affinitic/privatefolder/profiles/default/workflows/privatefolder_workflow/definition.xml
src/affinitic/privatefolder/profiles/uninstall/browserlayer.xml
src/affinitic/privatefolder/tests/__init__.py
src/affinitic/privatefolder/tests/test_setup.py