Metadata-Version: 2.1
Name: affinitic.privatefolder
Version: 1.0
Summary: Folderish content type with only one private state
Home-page: https://github.com/affinitic/affinitic.privatefolder
Author: Laurent Lasudry
Author-email: laurent.lasudry@affinitic.be
License: GPL version 2
Project-URL: Source, https://github.com/affinitic/affinitic.privatefolder
Project-URL: Tracker, https://github.com/affinitic/affinitic.privatefolder/issues
Project-URL: PyPI, https://pypi.python.org/pypi/affinitic.privatefolder
Keywords: Python Plone
Platform: UNKNOWN
Classifier: Environment :: Web Environment
Classifier: Framework :: Plone
Classifier: Framework :: Plone :: Addon
Classifier: Framework :: Plone :: 5.1
Classifier: Framework :: Plone :: 5.2
Classifier: Programming Language :: Python
Classifier: Programming Language :: Python :: 2.7
Classifier: Operating System :: OS Independent
Classifier: License :: OSI Approved :: GNU General Public License v2 (GPLv2)
Requires-Python: ==2.7
Provides-Extra: test
